afids_utils/__init__.py
afids_utils/afids.py
afids_utils/exceptions.py
afids_utils/ext/__init__.py
afids_utils/ext/fcsv.py
afids_utils/ext/json.py
afids_utils/metrics.py
afids_utils/plotting.py
afids_utils/py.typed
afids_utils/resources/__init__.py
afids_utils/resources/afids_descs.json
afids_utils/resources/template.fcsv
afids_utils/resources/template.json
afids_utils/transforms.py
afids_utils-0.2.0.dist-info/LICENSE
afids_utils-0.2.0.dist-info/METADATA
afids_utils-0.2.0.dist-info/WHEEL
afids_utils-0.2.0.dist-info/RECORD
