Metadata-Version: 2.1
Name: afids-utils
Version: 0.2.0
Summary: Utility functions for working with AFIDs data / workflows
License: MIT
Author: Jason Kai
Author-email: tkai@uwo.ca
Requires-Python: >=3.8,<3.12
Classifier: License :: OSI Approved :: MIT License
Classifier: Programming Language :: Python :: 3
Classifier: Programming Language :: Python :: 3.8
Classifier: Programming Language :: Python :: 3.9
Classifier: Programming Language :: Python :: 3.10
Classifier: Programming Language :: Python :: 3.11
Provides-Extra: plotting
Requires-Dist: attrs (>=23.1.0)
Requires-Dist: nilearn[plotting] (>=0.10.1) ; extra == "plotting"
Requires-Dist: numpy (>=1.24.3)
Requires-Dist: plotly (>=5.16.1) ; extra == "plotting"
